Metadata-Version: 1.0
Name: httpio
Version: 0.3.0
Summary: HTTP resources as random-access file-like objects
Home-page: https://github.com/barneygale/httpio
Author: Barney Gale
Author-email: barney@barneygale.co.uk
License: MIT
Platform: UNKNOWN
